znetwork/__init__.py
znetwork/mail.py
znetwork-1.0.0.dist-info/METADATA
znetwork-1.0.0.dist-info/WHEEL
znetwork-1.0.0.dist-info/licenses/LICENSE
znetwork-1.0.0.dist-info/RECORD
