Metadata-Version: 2.1
Name: znetwork
Version: 1.0.0
Summary: zen network library
Project-URL: Homepage, https://github.com/inspirare6/znetwork
Project-URL: Bug Tracker, https://github.com/inspirare6/znetwork/issues
Author-email: inspirare6 <inspirare6@163.com>
License-File: LICENSE
Classifier: License :: OSI Approved :: MIT License
Classifier: Operating System :: OS Independent
Classifier: Programming Language :: Python :: 3
Requires-Python: >=3.6
Requires-Dist: requests
